cat/__init__.py
cat/py.typed
cat/analysis/__init__.py
cat/analysis/core.py
cat/analysis/metrics.py
cat/analysis/metrics_ac.py
cat/analysis/metrics_basic.py
cat/analysis/metrics_tran.py
cat/analysis/montecarlo.py
cat/analysis/post.py
cat/analysis/step.py
cat/analysis/step_native.py
cat/analysis/sweep.py
cat/analysis/worstcase.py
cat/analysis/viz/plot.py
cat/core/__init__.py
cat/core/adc.py
cat/core/circuit.py
cat/core/components.py
cat/core/net.py
cat/core/typing.py
cat/dsl/__init__.py
cat/dsl/flow.py
cat/dsl/schematic.py
cat/io/__init__.py
cat/io/log_reader.py
cat/io/ltspice_asc.py
cat/io/ltspice_parser.py
cat/io/raw_reader.py
cat/io/spice_parser.py
cat/library/__init__.py
cat/library/capacitors.py
cat/library/diodes.py
cat/library/factory_typing.py
cat/library/importers.py
cat/library/inductors.py
cat/library/metadata.py
cat/library/opamps.py
cat/library/registry.py
cat/library/resistors.py
cat/library/switches.py
cat/library/transistors.py
cat/library/utils.py
cat/library/data/opamps/lm741.sub
cat/library/data/opamps/tl081.sub
cat/spice/__init__.py
cat/spice/base.py
cat/spice/ngspice_cli.py
cat/spice/registry.py
cat/utils/__init__.py
cat/utils/e_series.py
cat/utils/log.py
cat/utils/synth.py
cat/utils/topologies.py
cat/utils/units.py
cat/viz/__init__.py
cat/viz/plotly.py
pycircuitkit-0.2.2.dist-info/licenses/LICENSE
pycircuitkit-0.2.2.dist-info/METADATA
pycircuitkit-0.2.2.dist-info/WHEEL
pycircuitkit-0.2.2.dist-info/top_level.txt
pycircuitkit-0.2.2.dist-info/RECORD
