Metadata-Version: 2.4
Name: pycircuitkit
Version: 0.2.2
Summary: PyCircuitKit (CAT): Modern, strongly-typed Python toolkit for SPICE circuit definition, simulation and analysis.
Author: Luiz Carlos Gili
License: MIT
Project-URL: Homepage, https://github.com/lgili/PyCircuitKit
Project-URL: Repository, https://github.com/lgili/PyCircuitKit.git
Project-URL: Issues, https://github.com/lgili/PyCircuitKit/issues
Project-URL: Documentation, https://lgili.github.io/PyCircuitKit/
Keywords: spice,circuit,simulation,ngspice,electronics
Classifier: Development Status :: 3 - Alpha
Classifier: Intended Audience :: Science/Research
Classifier: License :: OSI Approved :: MIT License
Classifier: Programming Language :: Python :: 3
Classifier: Programming Language :: Python :: 3.10
Classifier: Programming Language :: Python :: 3.11
Classifier: Programming Language :: Python :: 3.12
Classifier: Topic :: Scientific/Engineering
Classifier: Topic :: Scientific/Engineering :: Electronic Design Automation (EDA)
Requires-Python: >=3.10
License-File: LICENSE
Requires-Dist: numpy>=1.26
Requires-Dist: pandas>=2.1
Requires-Dist: typing-extensions>=4.9
Provides-Extra: opt
Requires-Dist: scipy>=1.12; extra == "opt"
Provides-Extra: viz
Requires-Dist: plotly>=5.20; extra == "viz"
Requires-Dist: kaleido>=0.2.1; extra == "viz"
Dynamic: license-file
